[
  {
    "id": "H001",
    "name": "Hubble Tension Analysis",
    "domain": "Astrophysics",
    "description": "Pantheon+ SNe Ia (1701 supernovae) distance modulus analysis: test \u039bCDM predictions and measure H\u2080 tension",
    "confidence": 0.13253012048192778,
    "phase": "archived",
    "created_at": 1775459150.088852,
    "updated_at": 1775549594.525873,
    "test_results": [
      {
        "test_name": "Kolmogorov-Smirnov",
        "statistic": 0.018224573780129337,
        "p_value": 0.9402844576493801,
        "passed": true,
        "details": "D = 0.0182 (two-sample)",
        "alpha": 0.05
      },
      {
        "test_name": "Bayesian t-test",
        "statistic": -4642.0558950228415,
        "p_value": 0.0,
        "passed": true,
        "details": "t = -4642.0559 (one-sample vs \u03bc=0.0), n=1701",
        "alpha": 0.05
      },
      {
        "test_name": "Chi-squared",
        "statistic": 0.0035733553560542333,
        "p_value": 0.9999984057913186,
        "passed": true,
        "details": "\u03c7\u00b2 = 0.0036, dof = 4, \u03c7\u00b2/dof = 0.00",
        "alpha": 0.05
      },
      {
        "test_name": "Kolmogorov-Smirnov",
        "statistic": 0.018224573780129337,
        "p_value": 0.9402844576493801,
        "passed": true,
        "details": "D = 0.0182 (two-sample)",
        "alpha": 0.05
      },
      {
        "test_name": "Bayesian t-test",
        "statistic": -4642.0558950228415,
        "p_value": 0.0,
        "passed": true,
        "details": "t = -4642.0559 (one-sample vs \u03bc=0.0), n=1701",
        "alpha": 0.05
      },
      {
        "test_name": "Chi-squared",
        "statistic": 0.0035733553560542333,
        "p_value": 0.9999984057913186,
        "passed": true,
        "details": "\u03c7\u00b2 = 0.0036, dof = 4, \u03c7\u00b2/dof = 0.00",
        "alpha": 0.05
      },
      {
        "test_name": "Kolmogorov-Smirnov",
        "statistic": 0.018224573780129337,
        "p_value": 0.9402844576493801,
        "passed": true,
        "details": "D = 0.0182 (two-sample)",
        "alpha": 0.05
      },
      {
        "test_name": "Bayesian t-test",
        "statistic": -4642.0558950228415,
        "p_value": 0.0,
        "passed": true,
        "details": "t = -4642.0559 (one-sample vs \u03bc=0.0), n=1701",
        "alpha": 0.05
      },
      {
        "test_name": "Chi-squared",
        "statistic": 0.0035733553560542333,
        "p_value": 0.9999984057913186,
        "passed": true,
        "details": "\u03c7\u00b2 = 0.0036, dof = 4, \u03c7\u00b2/dof = 0.00",
        "alpha": 0.05
      }
    ],
    "priority": "NORMAL",
    "publications": 0,
    "data_points_used": 1701,
    "cross_domain_links": [],
    "requires_approval": false,
    "pending_approval_at": 0.0,
    "approval_status": "",
    "approval_reason": "",
    "last_tested_at": 1775549578.969574,
    "archived_at": 1775549594.525874
  },
  {
    "id": "H002",
    "name": "Galaxy Color Bimodality",
    "domain": "Astrophysics",
    "description": "SDSS DR18 galaxy photometry: quantify red sequence + blue cloud bimodality in g-r color",
    "confidence": 0.99,
    "phase": "published",
    "created_at": 1775339175.4631507,
    "updated_at": 1775549569.461005,
    "test_results": [
      {
        "test_name": "Kolmogorov-Smirnov",
        "statistic": 0.621614535084283,
        "p_value": 0.0,
        "passed": false,
        "details": "D = 0.6216 (vs norm)",
        "alpha": 0.05
      },
      {
        "test_name": "Chi-squared",
        "statistic": 4710.276,
        "p_value": 0.0,
        "passed": false,
        "details": "\u03c7\u00b2 = 4710.2760, dof = 9, \u03c7\u00b2/dof = 523.36",
        "alpha": 0.05
      },
      {
        "test_name": "Kolmogorov-Smirnov",
        "statistic": 0.621614535084283,
        "p_value": 0.0,
        "passed": false,
        "details": "D = 0.6216 (vs norm)",
        "alpha": 0.05
      },
      {
        "test_name": "Chi-squared",
        "statistic": 4710.276,
        "p_value": 0.0,
        "passed": false,
        "details": "\u03c7\u00b2 = 4710.2760, dof = 9, \u03c7\u00b2/dof = 523.36",
        "alpha": 0.05
      }
    ],
    "priority": "NORMAL",
    "publications": 0,
    "data_points_used": 10553,
    "cross_domain_links": [
      "CD-002"
    ],
    "requires_approval": false,
    "pending_approval_at": 1775549569.4523919,
    "approval_status": "approved",
    "approval_reason": "Auto-approved: confidence=0.99, tests=4, pending_cycles\u22480",
    "last_tested_at": 1775549569.114316,
    "archived_at": 0.0
  },
  {
    "id": "H003",
    "name": "Exoplanet Mass-Period Relation",
    "domain": "Astrophysics",
    "description": "NASA Exoplanet Archive: test Kepler's third law scaling and mass-period correlation in confirmed planets",
    "confidence": 0.99,
    "phase": "published",
    "created_at": 1775490287.9938705,
    "updated_at": 1775549594.537555,
    "test_results": [
      {
        "test_name": "Kolmogorov-Smirnov",
        "statistic": 1.0,
        "p_value": 0.0015564202334630343,
        "passed": false,
        "details": "D = 1.0000 (two-sample)",
        "alpha": 0.05
      },
      {
        "test_name": "Pearson correlation",
        "statistic": 0.43204120193240453,
        "p_value": 1.5685477197777295e-59,
        "passed": true,
        "details": "r = 0.4320, r\u00b2 = 0.1867",
        "alpha": 0.05
      },
      {
        "test_name": "Kolmogorov-Smirnov",
        "statistic": 1.0,
        "p_value": 0.0015564202334630343,
        "passed": false,
        "details": "D = 1.0000 (two-sample)",
        "alpha": 0.05
      },
      {
        "test_name": "Pearson correlation",
        "statistic": 0.43204120193240453,
        "p_value": 1.5685477197777295e-59,
        "passed": true,
        "details": "r = 0.4320, r\u00b2 = 0.1867",
        "alpha": 0.05
      }
    ],
    "priority": "NORMAL",
    "publications": 0,
    "data_points_used": 1284,
    "cross_domain_links": [
      "H024"
    ],
    "requires_approval": false,
    "pending_approval_at": 1775549569.4524999,
    "approval_status": "approved",
    "approval_reason": "Auto-approved: confidence=0.99, tests=4, pending_cycles\u22481",
    "last_tested_at": 1775549594.175209,
    "archived_at": 0.0
  },
  {
    "id": "H004",
    "name": "Gaia HR Diagram Structure",
    "domain": "Astrophysics",
    "description": "Gaia DR3 astrometry+photometry: characterize main sequence, giant branch, and white dwarf sequence",
    "confidence": 0.99,
    "phase": "published",
    "created_at": 1775337713.1004922,
    "updated_at": 1775551487.861551,
    "test_results": [
      {
        "test_name": "Kolmogorov-Smirnov",
        "statistic": 0.9999938333722036,
        "p_value": 0.0,
        "passed": false,
        "details": "D = 1.0000 (vs norm)",
        "alpha": 0.05
      },
      {
        "test_name": "Kolmogorov-Smirnov",
        "statistic": 0.9999938333722036,
        "p_value": 0.0,
        "passed": false,
        "details": "D = 1.0000 (vs norm)",
        "alpha": 0.05
      },
      {
        "test_name": "Kolmogorov-Smirnov",
        "statistic": 0.9999938333722036,
        "p_value": 0.0,
        "passed": false,
        "details": "D = 1.0000 (vs norm)",
        "alpha": 0.05
      }
    ],
    "priority": "HIGH",
    "publications": 0,
    "data_points_used": 5000,
    "cross_domain_links": [
      "H025"
    ],
    "requires_approval": false,
    "pending_approval_at": 1775551379.437354,
    "approval_status": "approved",
    "approval_reason": "Auto-approved: confidence=0.99, tests=3, pending_cycles\u22484",
    "last_tested_at": 1775551487.517855,
    "archived_at": 0.0
  },
  {
    "id": "H005",
    "name": "Galaxy Redshift Distribution",
    "domain": "Astrophysics",
    "description": "SDSS spectroscopic redshifts: test for clustering and void structure in local universe (z < 0.5)",
    "confidence": 0.99,
    "phase": "published",
    "created_at": 1775060054.7826254,
    "updated_at": 1775549651.413951,
    "test_results": [
      {
        "test_name": "Kolmogorov-Smirnov",
        "statistic": 0.621614535084283,
        "p_value": 0.0,
        "passed": false,
        "details": "D = 0.6216 (vs norm)",
        "alpha": 0.05
      },
      {
        "test_name": "Chi-squared",
        "statistic": 4710.276,
        "p_value": 0.0,
        "passed": false,
        "details": "\u03c7\u00b2 = 4710.2760, dof = 9, \u03c7\u00b2/dof = 523.36",
        "alpha": 0.05
      },
      {
        "test_name": "Kolmogorov-Smirnov",
        "statistic": 0.621614535084283,
        "p_value": 0.0,
        "passed": false,
        "details": "D = 0.6216 (vs norm)",
        "alpha": 0.05
      },
      {
        "test_name": "Chi-squared",
        "statistic": 4710.276,
        "p_value": 0.0,
        "passed": false,
        "details": "\u03c7\u00b2 = 4710.2760, dof = 9, \u03c7\u00b2/dof = 523.36",
        "alpha": 0.05
      }
    ],
    "priority": "NORMAL",
    "publications": 0,
    "data_points_used": 10553,
    "cross_domain_links": [
      "H026"
    ],
    "requires_approval": false,
    "pending_approval_at": 1775549594.5265138,
    "approval_status": "approved",
    "approval_reason": "Auto-approved: confidence=0.99, tests=4, pending_cycles\u22482",
    "last_tested_at": 1775549651.0430489,
    "archived_at": 0.0
  },
  {
    "id": "H006",
    "name": "Exoplanet Period Distribution",
    "domain": "Astrophysics",
    "description": "Transit/RV discoveries: test for period valley near 10 days and hot Jupiter desert",
    "confidence": 0.99,
    "phase": "published",
    "created_at": 1775356702.4652648,
    "updated_at": 1775549677.931564,
    "test_results": [
      {
        "test_name": "Kolmogorov-Smirnov",
        "statistic": 1.0,
        "p_value": 0.0015564202334630343,
        "passed": false,
        "details": "D = 1.0000 (two-sample)",
        "alpha": 0.05
      },
      {
        "test_name": "Pearson correlation",
        "statistic": 0.43204120193240453,
        "p_value": 1.5685477197777295e-59,
        "passed": true,
        "details": "r = 0.4320, r\u00b2 = 0.1867",
        "alpha": 0.05
      },
      {
        "test_name": "Kolmogorov-Smirnov",
        "statistic": 1.0,
        "p_value": 0.0015564202334630343,
        "passed": false,
        "details": "D = 1.0000 (two-sample)",
        "alpha": 0.05
      },
      {
        "test_name": "Pearson correlation",
        "statistic": 0.43204120193240453,
        "p_value": 1.5685477197777295e-59,
        "passed": true,
        "details": "r = 0.4320, r\u00b2 = 0.1867",
        "alpha": 0.05
      }
    ],
    "priority": "NORMAL",
    "publications": 0,
    "data_points_used": 1284,
    "cross_domain_links": [
      "H046"
    ],
    "requires_approval": false,
    "pending_approval_at": 1775549651.400351,
    "approval_status": "approved",
    "approval_reason": "Auto-approved: confidence=0.99, tests=4, pending_cycles\u22481",
    "last_tested_at": 1775549677.553503,
    "archived_at": 0.0
  },
  {
    "id": "H007",
    "name": "Stellar Parallax Accuracy",
    "domain": "Astrophysics",
    "description": "Gaia DR3 parallax error analysis: quantify systematic offsets and distance uncertainties",
    "confidence": 0.9770992366412214,
    "phase": "published",
    "created_at": 1775132227.5629807,
    "updated_at": 1775551520.931108,
    "test_results": [
      {
        "test_name": "Kolmogorov-Smirnov",
        "statistic": 0.9999938333722036,
        "p_value": 0.0,
        "passed": false,
        "details": "D = 1.0000 (vs norm)",
        "alpha": 0.05
      },
      {
        "test_name": "Kolmogorov-Smirnov",
        "statistic": 0.9999938333722036,
        "p_value": 0.0,
        "passed": false,
        "details": "D = 1.0000 (vs norm)",
        "alpha": 0.05
      }
    ],
    "priority": "NORMAL",
    "publications": 0,
    "data_points_used": 15553,
    "cross_domain_links": [],
    "requires_approval": false,
    "pending_approval_at": 1775551379.437472,
    "approval_status": "approved",
    "approval_reason": "Auto-approved: confidence=0.98, tests=2, pending_cycles\u22486",
    "last_tested_at": 1775551520.58923,
    "archived_at": 0.0
  },
  {
    "id": "H008",
    "name": "Star Formation Fraction",
    "domain": "Astrophysics",
    "description": "SDSS u-r color as star formation proxy: measure blue fraction evolution with redshift",
    "confidence": 0.8720379146919431,
    "phase": "published",
    "created_at": 1775488422.4979792,
    "updated_at": 1775551520.931108,
    "test_results": [
      {
        "test_name": "Kolmogorov-Smirnov",
        "statistic": 0.9999938333722036,
        "p_value": 0.0,
        "passed": false,
        "details": "D = 1.0000 (vs norm)",
        "alpha": 0.05
      }
    ],
    "priority": "MEDIUM",
    "publications": 0,
    "data_points_used": 5000,
    "cross_domain_links": [],
    "requires_approval": false,
    "pending_approval_at": 1775551379.437479,
    "approval_status": "approved",
    "approval_reason": "Auto-approved: confidence=0.87, tests=1, pending_cycles\u22486",
    "last_tested_at": 1775551293.844563,
    "archived_at": 0.0
  },
  {
    "id": "H009",
    "name": "Transit Depth Statistics",
    "domain": "Astrophysics",
    "description": "NASA Exoplanet Archive: distribution of transit depths across discovery methods",
    "confidence": 0.99,
    "phase": "published",
    "created_at": 1775194159.0336034,
    "updated_at": 1775551553.943892,
    "test_results": [
      {
        "test_name": "Kolmogorov-Smirnov",
        "statistic": 1.0,
        "p_value": 0.0015564202334630343,
        "passed": false,
        "details": "D = 1.0000 (two-sample)",
        "alpha": 0.05
      },
      {
        "test_name": "Pearson correlation",
        "statistic": 0.43204120193240453,
        "p_value": 1.5685477197777295e-59,
        "passed": true,
        "details": "r = 0.4320, r\u00b2 = 0.1867",
        "alpha": 0.05
      },
      {
        "test_name": "Kolmogorov-Smirnov",
        "statistic": 1.0,
        "p_value": 0.0015564202334630343,
        "passed": false,
        "details": "D = 1.0000 (two-sample)",
        "alpha": 0.05
      },
      {
        "test_name": "Pearson correlation",
        "statistic": 0.43204120193240453,
        "p_value": 1.5685477197777295e-59,
        "passed": true,
        "details": "r = 0.4320, r\u00b2 = 0.1867",
        "alpha": 0.05
      }
    ],
    "priority": "NORMAL",
    "publications": 0,
    "data_points_used": 1284,
    "cross_domain_links": [],
    "requires_approval": false,
    "pending_approval_at": 1775551487.8485372,
    "approval_status": "approved",
    "approval_reason": "Auto-approved: confidence=0.99, tests=4, pending_cycles\u22483",
    "last_tested_at": 1775551553.570645,
    "archived_at": 0.0
  },
  {
    "id": "H010",
    "name": "Dark Energy Equation of State",
    "domain": "Astrophysics",
    "description": "Pantheon+ distance modulus: constrain w(z) with binned SNe Ia analysis",
    "confidence": 0.11864406779661014,
    "phase": "archived",
    "created_at": 1775166543.1618335,
    "updated_at": 1775551487.8485498,
    "test_results": [
      {
        "test_name": "Kolmogorov-Smirnov",
        "statistic": 0.018224573780129337,
        "p_value": 0.9402844576493801,
        "passed": true,
        "details": "D = 0.0182 (two-sample)",
        "alpha": 0.05
      },
      {
        "test_name": "Bayesian t-test",
        "statistic": -4642.0558950228415,
        "p_value": 0.0,
        "passed": true,
        "details": "t = -4642.0559 (one-sample vs \u03bc=0.0), n=1701",
        "alpha": 0.05
      },
      {
        "test_name": "Chi-squared",
        "statistic": 0.0035733553560542333,
        "p_value": 0.9999984057913186,
        "passed": true,
        "details": "\u03c7\u00b2 = 0.0036, dof = 4, \u03c7\u00b2/dof = 0.00",
        "alpha": 0.05
      },
      {
        "test_name": "Kolmogorov-Smirnov",
        "statistic": 0.018224573780129337,
        "p_value": 0.9402844576493801,
        "passed": true,
        "details": "D = 0.0182 (two-sample)",
        "alpha": 0.05
      },
      {
        "test_name": "Bayesian t-test",
        "statistic": -4642.0558950228415,
        "p_value": 0.0,
        "passed": true,
        "details": "t = -4642.0559 (one-sample vs \u03bc=0.0), n=1701",
        "alpha": 0.05
      },
      {
        "test_name": "Chi-squared",
        "statistic": 0.0035733553560542333,
        "p_value": 0.9999984057913186,
        "passed": true,
        "details": "\u03c7\u00b2 = 0.0036, dof = 4, \u03c7\u00b2/dof = 0.00",
        "alpha": 0.05
      }
    ],
    "priority": "NORMAL",
    "publications": 0,
    "data_points_used": 1701,
    "cross_domain_links": [],
    "requires_approval": false,
    "pending_approval_at": 0.0,
    "approval_status": "",
    "approval_reason": "",
    "last_tested_at": 1775551484.0558531,
    "archived_at": 1775551487.848554
  },
  {
    "id": "H011",
    "name": "GW Mass Distribution",
    "domain": "Astrophysics",
    "description": "LIGO/Virgo chirp mass and mass ratio distribution: test population synthesis models",
    "confidence": 0.99,
    "phase": "published",
    "created_at": 1775308886.3039935,
    "updated_at": 1775551607.832451,
    "test_results": [
      {
        "test_name": "Kolmogorov-Smirnov",
        "statistic": 0.9999938333722036,
        "p_value": 0.0,
        "passed": false,
        "details": "D = 1.0000 (vs norm)",
        "alpha": 0.05
      },
      {
        "test_name": "Kolmogorov-Smirnov",
        "statistic": 0.9999938333722036,
        "p_value": 0.0,
        "passed": false,
        "details": "D = 1.0000 (vs norm)",
        "alpha": 0.05
      },
      {
        "test_name": "Kolmogorov-Smirnov",
        "statistic": 0.9999938333722036,
        "p_value": 0.0,
        "passed": false,
        "details": "D = 1.0000 (vs norm)",
        "alpha": 0.05
      }
    ],
    "priority": "NORMAL",
    "publications": 0,
    "data_points_used": 280,
    "cross_domain_links": [],
    "requires_approval": false,
    "pending_approval_at": 1775551487.848626,
    "approval_status": "approved",
    "approval_reason": "Auto-approved: confidence=0.99, tests=3, pending_cycles\u22485",
    "last_tested_at": 1775551607.478257,
    "archived_at": 0.0
  },
  {
    "id": "H012",
    "name": "CMB Acoustic Peak Structure",
    "domain": "Astrophysics",
    "description": "Planck TT power spectrum: measure acoustic peak positions and cosmological parameters",
    "confidence": 0.99,
    "phase": "published",
    "created_at": 1775327858.0282938,
    "updated_at": 1775551660.7025,
    "test_results": [
      {
        "test_name": "Kolmogorov-Smirnov",
        "statistic": 0.9999938333722036,
        "p_value": 0.0,
        "passed": false,
        "details": "D = 1.0000 (vs norm)",
        "alpha": 0.05
      },
      {
        "test_name": "Kolmogorov-Smirnov",
        "statistic": 0.9999938333722036,
        "p_value": 0.0,
        "passed": false,
        "details": "D = 1.0000 (vs norm)",
        "alpha": 0.05
      },
      {
        "test_name": "Kolmogorov-Smirnov",
        "statistic": 0.9999938333722036,
        "p_value": 0.0,
        "passed": false,
        "details": "D = 1.0000 (vs norm)",
        "alpha": 0.05
      }
    ],
    "priority": "NORMAL",
    "publications": 0,
    "data_points_used": 2507,
    "cross_domain_links": [],
    "requires_approval": false,
    "pending_approval_at": 1775551520.917711,
    "approval_status": "approved",
    "approval_reason": "Auto-approved: confidence=0.99, tests=3, pending_cycles\u22486",
    "last_tested_at": 1775551660.306615,
    "archived_at": 0.0
  },
  {
    "id": "H013",
    "name": "ZTF Transient Classification",
    "domain": "Astrophysics",
    "description": "ZTF transient light curves: test SNe classification and host galaxy association",
    "confidence": 0.8115942028985507,
    "phase": "published",
    "created_at": 1774971702.7981691,
    "updated_at": 1775551660.7025,
    "test_results": [
      {
        "test_name": "Kolmogorov-Smirnov",
        "statistic": 0.9999938333722036,
        "p_value": 0.0,
        "passed": false,
        "details": "D = 1.0000 (vs norm)",
        "alpha": 0.05
      }
    ],
    "priority": "NORMAL",
    "publications": 0,
    "data_points_used": 2000,
    "cross_domain_links": [],
    "requires_approval": false,
    "pending_approval_at": 1775551520.917721,
    "approval_status": "approved",
    "approval_reason": "Auto-approved: confidence=0.81, tests=1, pending_cycles\u22486",
    "last_tested_at": 1775551484.506216,
    "archived_at": 0.0
  },
  {
    "id": "H014",
    "name": "TESS Stellar Host Parameters",
    "domain": "Astrophysics",
    "description": "TESS Input Catalog: mass-radius relation for exoplanet host stars",
    "confidence": 0.9788783685360525,
    "phase": "published",
    "created_at": 1775279464.0793087,
    "updated_at": 1775551687.05643,
    "test_results": [
      {
        "test_name": "Kolmogorov-Smirnov",
        "statistic": 0.9999938333722036,
        "p_value": 0.0,
        "passed": false,
        "details": "D = 1.0000 (vs norm)",
        "alpha": 0.05
      },
      {
        "test_name": "Kolmogorov-Smirnov",
        "statistic": 0.9999938333722036,
        "p_value": 0.0,
        "passed": false,
        "details": "D = 1.0000 (vs norm)",
        "alpha": 0.05
      }
    ],
    "priority": "NORMAL",
    "publications": 0,
    "data_points_used": 15553,
    "cross_domain_links": [],
    "requires_approval": false,
    "pending_approval_at": 1775551553.925022,
    "approval_status": "approved",
    "approval_reason": "Auto-approved: confidence=0.98, tests=2, pending_cycles\u22485",
    "last_tested_at": 1775551686.7052422,
    "archived_at": 0.0
  },
  {
    "id": "H015",
    "name": "Cluster Richness-Mass Scaling",
    "domain": "Astrophysics",
    "description": "SDSS redMaPPer richness as mass proxy: test self-similar scaling relation",
    "confidence": 0.8306010928961749,
    "phase": "published",
    "created_at": 1775487940.1715267,
    "updated_at": 1775551687.05643,
    "test_results": [
      {
        "test_name": "Kolmogorov-Smirnov",
        "statistic": 0.9999938333722036,
        "p_value": 0.0,
        "passed": false,
        "details": "D = 1.0000 (vs norm)",
        "alpha": 0.05
      }
    ],
    "priority": "NORMAL",
    "publications": 0,
    "data_points_used": 15553,
    "cross_domain_links": [],
    "requires_approval": false,
    "pending_approval_at": 1775551553.925048,
    "approval_status": "approved",
    "approval_reason": "Auto-approved: confidence=0.83, tests=1, pending_cycles\u22485",
    "last_tested_at": 1775551514.548592,
    "archived_at": 0.0
  },
  {
    "id": "H016",
    "name": "GW Electromagnetic Counterpart",
    "domain": "Astrophysics",
    "description": "Cross-match GW events with ZTF transients for multi-messenger association",
    "confidence": 0.964824120603015,
    "phase": "published",
    "created_at": 1775447932.9260674,
    "updated_at": 1775551713.4553201,
    "test_results": [
      {
        "test_name": "Kolmogorov-Smirnov",
        "statistic": 0.9999938333722036,
        "p_value": 0.0,
        "passed": false,
        "details": "D = 1.0000 (vs norm)",
        "alpha": 0.05
      },
      {
        "test_name": "Kolmogorov-Smirnov",
        "statistic": 0.9999938333722036,
        "p_value": 0.0,
        "passed": false,
        "details": "D = 1.0000 (vs norm)",
        "alpha": 0.05
      }
    ],
    "priority": "NORMAL",
    "publications": 0,
    "data_points_used": 280,
    "cross_domain_links": [],
    "requires_approval": false,
    "pending_approval_at": 1775551553.925059,
    "approval_status": "approved",
    "approval_reason": "Auto-approved: confidence=0.96, tests=2, pending_cycles\u22486",
    "last_tested_at": 1775551713.066742,
    "archived_at": 0.0
  },
  {
    "id": "H017",
    "name": "Stellar TESS-Gaia Cross-Match",
    "domain": "Astrophysics",
    "description": "Link TESS host stars with Gaia astrometry for precise distance-luminosity calibration",
    "confidence": 0.8115942028985507,
    "phase": "published",
    "created_at": 1775360103.637316,
    "updated_at": 1775551713.4553201,
    "test_results": [
      {
        "test_name": "Kolmogorov-Smirnov",
        "statistic": 0.9999938333722036,
        "p_value": 0.0,
        "passed": false,
        "details": "D = 1.0000 (vs norm)",
        "alpha": 0.05
      }
    ],
    "priority": "NORMAL",
    "publications": 0,
    "data_points_used": 15553,
    "cross_domain_links": [],
    "requires_approval": false,
    "pending_approval_at": 1775551580.9440799,
    "approval_status": "approved",
    "approval_reason": "Auto-approved: confidence=0.81, tests=1, pending_cycles\u22485",
    "last_tested_at": 1775551547.058631,
    "archived_at": 0.0
  },
  {
    "id": "CD-001",
    "name": "Econ-Astro Funding Correlation",
    "domain": "Economics",
    "description": "Correlation between national R&D funding and astronomical discovery rates",
    "confidence": 0.25,
    "phase": "proposed",
    "created_at": 1775147309.082293,
    "updated_at": 1775549456.237227,
    "test_results": [],
    "priority": "HIGH",
    "publications": 0,
    "data_points_used": 0,
    "cross_domain_links": [],
    "requires_approval": false,
    "pending_approval_at": 0.0,
    "approval_status": "",
    "approval_reason": "",
    "last_tested_at": 0.0,
    "archived_at": 0.0
  },
  {
    "id": "CD-002",
    "name": "Survey Design Optimization",
    "domain": "Epidemiology",
    "description": "Apply epidemiological adaptive sampling to astronomical survey strategy",
    "confidence": 0.964824120603015,
    "phase": "published",
    "created_at": 1774973543.6567142,
    "updated_at": 1775551739.801908,
    "test_results": [
      {
        "test_name": "Kolmogorov-Smirnov",
        "statistic": 0.9999938333722036,
        "p_value": 0.0,
        "passed": false,
        "details": "D = 1.0000 (vs norm)",
        "alpha": 0.05
      },
      {
        "test_name": "Kolmogorov-Smirnov",
        "statistic": 0.9999938333722036,
        "p_value": 0.0,
        "passed": false,
        "details": "D = 1.0000 (vs norm)",
        "alpha": 0.05
      }
    ],
    "priority": "NORMAL",
    "publications": 0,
    "data_points_used": 15553,
    "cross_domain_links": [
      "H002"
    ],
    "requires_approval": false,
    "pending_approval_at": 1775551580.944106,
    "approval_status": "approved",
    "approval_reason": "Auto-approved: confidence=0.96, tests=2, pending_cycles\u22486",
    "last_tested_at": 1775551739.458266,
    "archived_at": 0.0
  },
  {
    "id": "H018",
    "name": "GDP-Inequality Nexus",
    "domain": "Economics",
    "description": "Test Kuznets curve and Gini-GDP relationship across countries. Bayesian model comparison for linear vs inverted-U vs no relationship.",
    "confidence": 0.2,
    "phase": "proposed",
    "created_at": 1775549517.848883,
    "updated_at": 1775549517.848883,
    "test_results": [],
    "priority": "MEDIUM",
    "publications": 0,
    "data_points_used": 0,
    "cross_domain_links": [],
    "requires_approval": false,
    "pending_approval_at": 0.0,
    "approval_status": "",
    "approval_reason": "",
    "last_tested_at": 0.0,
    "archived_at": 0.0
  },
  {
    "id": "H019",
    "name": "Trade Network Structure",
    "domain": "Economics",
    "description": "Analyze global trade network topology. Test scale-free properties, hub-and-spoke structure, and trade flow power laws.",
    "confidence": 0.2,
    "phase": "proposed",
    "created_at": 1775549517.8488991,
    "updated_at": 1775549517.8488991,
    "test_results": [],
    "priority": "NORMAL",
    "publications": 0,
    "data_points_used": 0,
    "cross_domain_links": [],
    "requires_approval": false,
    "pending_approval_at": 0.0,
    "approval_status": "",
    "approval_reason": "",
    "last_tested_at": 0.0,
    "archived_at": 0.0
  },
  {
    "id": "H020",
    "name": "Inflation-Growth Dynamics",
    "domain": "Economics",
    "description": "Investigate nonlinear inflation\u2013growth relationship across economies. Threshold regression to find optimal inflation ranges.",
    "confidence": 0.2,
    "phase": "proposed",
    "created_at": 1775549569.460587,
    "updated_at": 1775549569.460587,
    "test_results": [],
    "priority": "NORMAL",
    "publications": 0,
    "data_points_used": 0,
    "cross_domain_links": [],
    "requires_approval": false,
    "pending_approval_at": 0.0,
    "approval_status": "",
    "approval_reason": "",
    "last_tested_at": 0.0,
    "archived_at": 0.0
  },
  {
    "id": "H021",
    "name": "CO2-Temperature Attribution",
    "domain": "Climate",
    "description": "Quantify CO2 forcing contribution to observed warming using Granger causality and attribution analysis on instrumental records.",
    "confidence": 0.2,
    "phase": "proposed",
    "created_at": 1775549569.460608,
    "updated_at": 1775549569.460608,
    "test_results": [],
    "priority": "NORMAL",
    "publications": 0,
    "data_points_used": 0,
    "cross_domain_links": [],
    "requires_approval": false,
    "pending_approval_at": 0.0,
    "approval_status": "",
    "approval_reason": "",
    "last_tested_at": 0.0,
    "archived_at": 0.0
  },
  {
    "id": "H022",
    "name": "Extreme Weather Trends",
    "domain": "Climate",
    "description": "Statistical analysis of extreme weather event frequency trends. Fit GEV distributions, test for changing return periods.",
    "confidence": 0.2,
    "phase": "proposed",
    "created_at": 1775549594.536876,
    "updated_at": 1775549594.536876,
    "test_results": [],
    "priority": "NORMAL",
    "publications": 0,
    "data_points_used": 0,
    "cross_domain_links": [],
    "requires_approval": false,
    "pending_approval_at": 0.0,
    "approval_status": "",
    "approval_reason": "",
    "last_tested_at": 0.0,
    "archived_at": 0.0
  },
  {
    "id": "H023",
    "name": "Sea Level Acceleration",
    "domain": "Climate",
    "description": "Test for acceleration in sea level rise using tide gauge + satellite altimetry data. Quadratic vs linear trend comparison.",
    "confidence": 0.2,
    "phase": "proposed",
    "created_at": 1775549594.536911,
    "updated_at": 1775549594.536911,
    "test_results": [],
    "priority": "NORMAL",
    "publications": 0,
    "data_points_used": 0,
    "cross_domain_links": [],
    "requires_approval": false,
    "pending_approval_at": 0.0,
    "approval_status": "",
    "approval_reason": "",
    "last_tested_at": 0.0,
    "archived_at": 0.0
  },
  {
    "id": "H024",
    "name": "Vaccination-Mortality Reduction",
    "domain": "Epidemiology",
    "description": "Quantify causal effect of DPT/measles vaccination coverage on under-5 mortality rates. Instrumental variable + panel data approach.",
    "confidence": 0.2,
    "phase": "proposed",
    "created_at": 1775549651.4131908,
    "updated_at": 1775549651.4131908,
    "test_results": [],
    "priority": "NORMAL",
    "publications": 0,
    "data_points_used": 0,
    "cross_domain_links": [
      "H003"
    ],
    "requires_approval": false,
    "pending_approval_at": 0.0,
    "approval_status": "",
    "approval_reason": "",
    "last_tested_at": 0.0,
    "archived_at": 0.0
  },
  {
    "id": "H025",
    "name": "Preston Curve Evolution",
    "domain": "Epidemiology",
    "description": "Test whether the Preston curve (income vs life expectancy) has shifted upward over decades. Time-varying coefficient analysis.",
    "confidence": 0.2,
    "phase": "proposed",
    "created_at": 1775549651.413236,
    "updated_at": 1775549651.413236,
    "test_results": [],
    "priority": "NORMAL",
    "publications": 0,
    "data_points_used": 0,
    "cross_domain_links": [
      "H004"
    ],
    "requires_approval": false,
    "pending_approval_at": 0.0,
    "approval_status": "",
    "approval_reason": "",
    "last_tested_at": 0.0,
    "archived_at": 0.0
  },
  {
    "id": "H026",
    "name": "Disease Burden Inequality",
    "domain": "Epidemiology",
    "description": "Analyze concentration of disease burden by income quintile. Gini-like health inequality metrics across countries and time.",
    "confidence": 0.2,
    "phase": "proposed",
    "created_at": 1775549677.916866,
    "updated_at": 1775549677.916866,
    "test_results": [],
    "priority": "NORMAL",
    "publications": 0,
    "data_points_used": 0,
    "cross_domain_links": [
      "H005"
    ],
    "requires_approval": false,
    "pending_approval_at": 0.0,
    "approval_status": "",
    "approval_reason": "",
    "last_tested_at": 0.0,
    "archived_at": 0.0
  },
  {
    "id": "H027",
    "name": "Wealth-Health-Climate Triad",
    "domain": "Cross-Domain",
    "description": "Three-way interaction: GDP per capita, life expectancy, and CO2 emissions. Test Environmental Kuznets Curve with health co-benefits.",
    "confidence": 0.2,
    "phase": "proposed",
    "created_at": 1775549677.919467,
    "updated_at": 1775549677.919467,
    "test_results": [],
    "priority": "NORMAL",
    "publications": 0,
    "data_points_used": 0,
    "cross_domain_links": [],
    "requires_approval": false,
    "pending_approval_at": 0.0,
    "approval_status": "",
    "approval_reason": "",
    "last_tested_at": 0.0,
    "archived_at": 0.0
  },
  {
    "id": "H028",
    "name": "Urbanization Cascade",
    "domain": "Cross-Domain",
    "description": "Urbanization \u2192 economic growth \u2192 emissions \u2192 health impacts causal chain. Structural equation modeling across 150+ countries.",
    "confidence": 0.2,
    "phase": "proposed",
    "created_at": 1775549704.415909,
    "updated_at": 1775549704.415909,
    "test_results": [],
    "priority": "NORMAL",
    "publications": 0,
    "data_points_used": 0,
    "cross_domain_links": [],
    "requires_approval": false,
    "pending_approval_at": 0.0,
    "approval_status": "",
    "approval_reason": "",
    "last_tested_at": 0.0,
    "archived_at": 0.0
  },
  {
    "id": "H029",
    "name": "EXOPLANETS Period-Mass Probe",
    "domain": "Astrophysics",
    "description": "Novel exploration of period\u2013mass relation in exoplanets data. Untested variable pair \u2014 first measurement.",
    "confidence": 0.15,
    "phase": "proposed",
    "created_at": 1775549730.9430048,
    "updated_at": 1775549730.9430048,
    "test_results": [],
    "priority": "NORMAL",
    "publications": 0,
    "data_points_used": 0,
    "cross_domain_links": [],
    "requires_approval": false,
    "pending_approval_at": 0.0,
    "approval_status": "",
    "approval_reason": "",
    "last_tested_at": 0.0,
    "archived_at": 0.0
  },
  {
    "id": "H030",
    "name": "EXOPLANETS Period-Radius Probe",
    "domain": "Astrophysics",
    "description": "Novel exploration of period\u2013radius relation in exoplanets data. Untested variable pair \u2014 first measurement.",
    "confidence": 0.15,
    "phase": "proposed",
    "created_at": 1775549730.943084,
    "updated_at": 1775549730.943084,
    "test_results": [],
    "priority": "NORMAL",
    "publications": 0,
    "data_points_used": 0,
    "cross_domain_links": [],
    "requires_approval": false,
    "pending_approval_at": 0.0,
    "approval_status": "",
    "approval_reason": "",
    "last_tested_at": 0.0,
    "archived_at": 0.0
  },
  {
    "id": "H031",
    "name": "SDSS Redshift-U_G Probe",
    "domain": "Astrophysics",
    "description": "Novel exploration of redshift\u2013u_g relation in sdss data. Untested variable pair \u2014 first measurement.",
    "confidence": 0.15,
    "phase": "proposed",
    "created_at": 1775549730.9431849,
    "updated_at": 1775549730.9431849,
    "test_results": [],
    "priority": "NORMAL",
    "publications": 0,
    "data_points_used": 0,
    "cross_domain_links": [],
    "requires_approval": false,
    "pending_approval_at": 0.0,
    "approval_status": "",
    "approval_reason": "",
    "last_tested_at": 0.0,
    "archived_at": 0.0
  },
  {
    "id": "H032",
    "name": "SDSS Redshift-G_R Probe",
    "domain": "Astrophysics",
    "description": "Novel exploration of redshift\u2013g_r relation in sdss data. Untested variable pair \u2014 first measurement.",
    "confidence": 0.15,
    "phase": "proposed",
    "created_at": 1775549730.9432058,
    "updated_at": 1775549730.9432058,
    "test_results": [],
    "priority": "NORMAL",
    "publications": 0,
    "data_points_used": 0,
    "cross_domain_links": [],
    "requires_approval": false,
    "pending_approval_at": 0.0,
    "approval_status": "",
    "approval_reason": "",
    "last_tested_at": 0.0,
    "archived_at": 0.0
  },
  {
    "id": "H033",
    "name": "GAIA Parallax-Gmag Probe",
    "domain": "Astrophysics",
    "description": "Novel exploration of parallax\u2013gmag relation in gaia data. Untested variable pair \u2014 first measurement.",
    "confidence": 0.15,
    "phase": "proposed",
    "created_at": 1775549730.943237,
    "updated_at": 1775549730.943237,
    "test_results": [],
    "priority": "NORMAL",
    "publications": 0,
    "data_points_used": 0,
    "cross_domain_links": [],
    "requires_approval": false,
    "pending_approval_at": 0.0,
    "approval_status": "",
    "approval_reason": "",
    "last_tested_at": 0.0,
    "archived_at": 0.0
  },
  {
    "id": "H034",
    "name": "GAIA Parallax-Bp_Rp Probe",
    "domain": "Astrophysics",
    "description": "Novel exploration of parallax\u2013bp_rp relation in gaia data. Untested variable pair \u2014 first measurement.",
    "confidence": 0.15,
    "phase": "proposed",
    "created_at": 1775549757.427211,
    "updated_at": 1775549757.427211,
    "test_results": [],
    "priority": "NORMAL",
    "publications": 0,
    "data_points_used": 0,
    "cross_domain_links": [],
    "requires_approval": false,
    "pending_approval_at": 0.0,
    "approval_status": "",
    "approval_reason": "",
    "last_tested_at": 0.0,
    "archived_at": 0.0
  },
  {
    "id": "H035",
    "name": "PANTHEON Zhd-M_B Probe",
    "domain": "Astrophysics",
    "description": "Novel exploration of zHD\u2013m_b relation in pantheon data. Untested variable pair \u2014 first measurement.",
    "confidence": 0.15,
    "phase": "proposed",
    "created_at": 1775549757.427253,
    "updated_at": 1775549757.427253,
    "test_results": [],
    "priority": "NORMAL",
    "publications": 0,
    "data_points_used": 0,
    "cross_domain_links": [],
    "requires_approval": false,
    "pending_approval_at": 0.0,
    "approval_status": "",
    "approval_reason": "",
    "last_tested_at": 0.0,
    "archived_at": 0.0
  },
  {
    "id": "H036",
    "name": "PANTHEON Zhd-M_B_Err Probe",
    "domain": "Astrophysics",
    "description": "Novel exploration of zHD\u2013m_b_err relation in pantheon data. Untested variable pair \u2014 first measurement.",
    "confidence": 0.15,
    "phase": "proposed",
    "created_at": 1775549757.42727,
    "updated_at": 1775549757.42727,
    "test_results": [],
    "priority": "NORMAL",
    "publications": 0,
    "data_points_used": 0,
    "cross_domain_links": [],
    "requires_approval": false,
    "pending_approval_at": 0.0,
    "approval_status": "",
    "approval_reason": "",
    "last_tested_at": 0.0,
    "archived_at": 0.0
  },
  {
    "id": "H037",
    "name": "Theoretical: Black Hole Information Paradox",
    "domain": "Astrophysics",
    "description": "Paradox analysis: Black holes appear to destroy information, violating quantum unitarity. Implications: ['Quantum gravity must preserve unitarity', 'Spacetime may be emergent from entanglement']",
    "confidence": 0.25,
    "phase": "proposed",
    "created_at": 1775550077.288345,
    "updated_at": 1775550077.288345,
    "test_results": [],
    "priority": "NORMAL",
    "publications": 0,
    "data_points_used": 0,
    "cross_domain_links": [],
    "requires_approval": false,
    "pending_approval_at": 0.0,
    "approval_status": "",
    "approval_reason": "",
    "last_tested_at": 0.0,
    "archived_at": 0.0
  },
  {
    "id": "H038",
    "name": "Theoretical: Entropic Gravity Deep-MOND (Entropic)",
    "domain": "Astrophysics",
    "description": "Information-theoretic prediction: At a = 7.008e-41 m/s\u00b2: Entropic suppression. Newtonian a=7.008e-41 m/s\u00b2, Entropic a=9.171e-26 m/s\u00b2.",
    "confidence": 0.964824120603015,
    "phase": "published",
    "created_at": 1775550342.815517,
    "updated_at": 1775551766.185722,
    "test_results": [
      {
        "test_name": "Kolmogorov-Smirnov",
        "statistic": 0.9999938333722036,
        "p_value": 0.0,
        "passed": false,
        "details": "D = 1.0000 (vs norm)",
        "alpha": 0.05
      },
      {
        "test_name": "Kolmogorov-Smirnov",
        "statistic": 0.9999938333722036,
        "p_value": 0.0,
        "passed": false,
        "details": "D = 1.0000 (vs norm)",
        "alpha": 0.05
      }
    ],
    "priority": "NORMAL",
    "publications": 0,
    "data_points_used": 5000,
    "cross_domain_links": [],
    "requires_approval": false,
    "pending_approval_at": 1775551580.944173,
    "approval_status": "approved",
    "approval_reason": "Auto-approved: confidence=0.96, tests=2, pending_cycles\u22487",
    "last_tested_at": 1775551765.8018088,
    "archived_at": 0.0
  },
  {
    "id": "H039",
    "name": "Theoretical: Black Hole Information Paradox",
    "domain": "Astrophysics",
    "description": "Paradox analysis: Black holes appear to destroy information, violating quantum unitarity. Implications: ['Quantum gravity must preserve unitarity', 'Spacetime may be emergent from entanglement']",
    "confidence": 0.25,
    "phase": "proposed",
    "created_at": 1775550342.8157609,
    "updated_at": 1775550342.8157618,
    "test_results": [],
    "priority": "NORMAL",
    "publications": 0,
    "data_points_used": 0,
    "cross_domain_links": [],
    "requires_approval": false,
    "pending_approval_at": 0.0,
    "approval_status": "",
    "approval_reason": "",
    "last_tested_at": 0.0,
    "archived_at": 0.0
  },
  {
    "id": "H040",
    "name": "Theoretical: Multi-Method Analysis",
    "domain": "Astrophysics",
    "description": "Tree search found 51 methods. Best score: 0.990",
    "confidence": 0.8399150972979896,
    "phase": "published",
    "created_at": 1775550342.81837,
    "updated_at": 1775551739.801908,
    "test_results": [
      {
        "test_name": "Kolmogorov-Smirnov",
        "statistic": 0.9999938333722036,
        "p_value": 0.0,
        "passed": false,
        "details": "D = 1.0000 (vs norm)",
        "alpha": 0.05
      }
    ],
    "priority": "NORMAL",
    "publications": 0,
    "data_points_used": 15553,
    "cross_domain_links": [],
    "requires_approval": false,
    "pending_approval_at": 1775551607.807294,
    "approval_status": "approved",
    "approval_reason": "Auto-approved: confidence=0.84, tests=1, pending_cycles\u22485",
    "last_tested_at": 1775551580.213223,
    "archived_at": 0.0
  },
  {
    "id": "H041",
    "name": "Theoretical: Entropic Gravity Deep-MOND (Entropic)",
    "domain": "Astrophysics",
    "description": "Information-theoretic prediction: At a = 7.008e-41 m/s\u00b2: Entropic suppression. Newtonian a=7.008e-41 m/s\u00b2, Entropic a=9.171e-26 m/s\u00b2.",
    "confidence": 0.964824120603015,
    "phase": "published",
    "created_at": 1775550608.910788,
    "updated_at": 1775551792.60621,
    "test_results": [
      {
        "test_name": "Kolmogorov-Smirnov",
        "statistic": 0.9999938333722036,
        "p_value": 0.0,
        "passed": false,
        "details": "D = 1.0000 (vs norm)",
        "alpha": 0.05
      },
      {
        "test_name": "Kolmogorov-Smirnov",
        "statistic": 0.9999938333722036,
        "p_value": 0.0,
        "passed": false,
        "details": "D = 1.0000 (vs norm)",
        "alpha": 0.05
      }
    ],
    "priority": "NORMAL",
    "publications": 0,
    "data_points_used": 15553,
    "cross_domain_links": [],
    "requires_approval": false,
    "pending_approval_at": 1775551607.8073092,
    "approval_status": "approved",
    "approval_reason": "Auto-approved: confidence=0.96, tests=2, pending_cycles\u22487",
    "last_tested_at": 1775551792.1896079,
    "archived_at": 0.0
  },
  {
    "id": "H042",
    "name": "Theoretical: Black Hole Information Paradox",
    "domain": "Astrophysics",
    "description": "Paradox analysis: Black holes appear to destroy information, violating quantum unitarity. Implications: ['Quantum gravity must preserve unitarity', 'Spacetime may be emergent from entanglement']",
    "confidence": 0.25,
    "phase": "proposed",
    "created_at": 1775550877.21575,
    "updated_at": 1775550877.215751,
    "test_results": [],
    "priority": "NORMAL",
    "publications": 0,
    "data_points_used": 0,
    "cross_domain_links": [],
    "requires_approval": false,
    "pending_approval_at": 0.0,
    "approval_status": "",
    "approval_reason": "",
    "last_tested_at": 0.0,
    "archived_at": 0.0
  },
  {
    "id": "H043",
    "name": "Theoretical: Entropic Gravity Deep-MOND (Entropic)",
    "domain": "Astrophysics",
    "description": "Information-theoretic prediction: At a = 7.008e-41 m/s\u00b2: Entropic suppression. Newtonian a=7.008e-41 m/s\u00b2, Entropic a=9.171e-26 m/s\u00b2.",
    "confidence": 0.964824120603015,
    "phase": "published",
    "created_at": 1775551142.644458,
    "updated_at": 1775551818.9767418,
    "test_results": [
      {
        "test_name": "Kolmogorov-Smirnov",
        "statistic": 0.9999938333722036,
        "p_value": 0.0,
        "passed": false,
        "details": "D = 1.0000 (vs norm)",
        "alpha": 0.05
      },
      {
        "test_name": "Kolmogorov-Smirnov",
        "statistic": 0.9999938333722036,
        "p_value": 0.0,
        "passed": false,
        "details": "D = 1.0000 (vs norm)",
        "alpha": 0.05
      }
    ],
    "priority": "NORMAL",
    "publications": 0,
    "data_points_used": 5000,
    "cross_domain_links": [],
    "requires_approval": false,
    "pending_approval_at": 1775551607.807317,
    "approval_status": "approved",
    "approval_reason": "Auto-approved: confidence=0.96, tests=2, pending_cycles\u22488",
    "last_tested_at": 1775551818.602062,
    "archived_at": 0.0
  },
  {
    "id": "H044",
    "name": "Theoretical: Black Hole Information Paradox",
    "domain": "Astrophysics",
    "description": "Paradox analysis: Black holes appear to destroy information, violating quantum unitarity. Implications: ['Quantum gravity must preserve unitarity', 'Spacetime may be emergent from entanglement']",
    "confidence": 0.25,
    "phase": "proposed",
    "created_at": 1775551142.644563,
    "updated_at": 1775551142.644563,
    "test_results": [],
    "priority": "NORMAL",
    "publications": 0,
    "data_points_used": 0,
    "cross_domain_links": [],
    "requires_approval": false,
    "pending_approval_at": 0.0,
    "approval_status": "",
    "approval_reason": "",
    "last_tested_at": 0.0,
    "archived_at": 0.0
  },
  {
    "id": "H045",
    "name": "Theoretical: Multi-Method Analysis",
    "domain": "Astrophysics",
    "description": "Tree search found 54 methods. Best score: 0.992",
    "confidence": 0.8403355414045126,
    "phase": "published",
    "created_at": 1775551142.647294,
    "updated_at": 1775551766.185722,
    "test_results": [
      {
        "test_name": "Kolmogorov-Smirnov",
        "statistic": 0.9999938333722036,
        "p_value": 0.0,
        "passed": false,
        "details": "D = 1.0000 (vs norm)",
        "alpha": 0.05
      }
    ],
    "priority": "NORMAL",
    "publications": 0,
    "data_points_used": 5000,
    "cross_domain_links": [],
    "requires_approval": false,
    "pending_approval_at": 1775551634.223409,
    "approval_status": "approved",
    "approval_reason": "Auto-approved: confidence=0.84, tests=1, pending_cycles\u22485",
    "last_tested_at": 1775551607.067071,
    "archived_at": 0.0
  },
  {
    "id": "H046",
    "name": "Cross-Domain: Correlation from Astrophysics\u2192Epidemiology",
    "domain": "Epidemiology",
    "description": "Does the correlation pattern observed in Astrophysics (Pearson correlation: r = 0.4320, r\u00b2 = 0.1867) have an analog in Epidemiology? Structural comparison across domains.",
    "confidence": 0.12,
    "phase": "proposed",
    "created_at": 1775551553.940725,
    "updated_at": 1775551553.940725,
    "test_results": [],
    "priority": "NORMAL",
    "publications": 0,
    "data_points_used": 0,
    "cross_domain_links": [
      "H006"
    ],
    "requires_approval": false,
    "pending_approval_at": 0.0,
    "approval_status": "",
    "approval_reason": "",
    "last_tested_at": 0.0,
    "archived_at": 0.0
  },
  {
    "id": "H047",
    "name": "Theoretical: Entropic Gravity Deep-MOND (Entropic)",
    "domain": "Astrophysics",
    "description": "Information-theoretic prediction: At a = 7.008e-41 m/s\u00b2: Entropic suppression. Newtonian a=7.008e-41 m/s\u00b2, Entropic a=9.171e-26 m/s\u00b2.",
    "confidence": 0.964824120603015,
    "phase": "published",
    "created_at": 1775551580.952107,
    "updated_at": 1775551845.948925,
    "test_results": [
      {
        "test_name": "Kolmogorov-Smirnov",
        "statistic": 0.9999938333722036,
        "p_value": 0.0,
        "passed": false,
        "details": "D = 1.0000 (vs norm)",
        "alpha": 0.05
      },
      {
        "test_name": "Kolmogorov-Smirnov",
        "statistic": 0.9999938333722036,
        "p_value": 0.0,
        "passed": false,
        "details": "D = 1.0000 (vs norm)",
        "alpha": 0.05
      }
    ],
    "priority": "NORMAL",
    "publications": 0,
    "data_points_used": 15553,
    "cross_domain_links": [],
    "requires_approval": false,
    "pending_approval_at": 1775551634.223428,
    "approval_status": "approved",
    "approval_reason": "Auto-approved: confidence=0.96, tests=2, pending_cycles\u22488",
    "last_tested_at": 1775551844.959041,
    "archived_at": 0.0
  },
  {
    "id": "H048",
    "name": "Theoretical: Black Hole Information Paradox",
    "domain": "Astrophysics",
    "description": "Paradox analysis: Black holes appear to destroy information, violating quantum unitarity. Implications: ['Quantum gravity must preserve unitarity', 'Spacetime may be emergent from entanglement']",
    "confidence": 0.25,
    "phase": "proposed",
    "created_at": 1775551580.9521868,
    "updated_at": 1775551580.9521868,
    "test_results": [],
    "priority": "NORMAL",
    "publications": 0,
    "data_points_used": 0,
    "cross_domain_links": [],
    "requires_approval": false,
    "pending_approval_at": 0.0,
    "approval_status": "",
    "approval_reason": "",
    "last_tested_at": 0.0,
    "archived_at": 0.0
  },
  {
    "id": "H049",
    "name": "Theoretical: Unitarity (from quantum_mechanics) \u2192 black_holes",
    "domain": "Astrophysics",
    "description": "Constraint transfer: Unitarity (from quantum_mechanics) \u2192 black_holes. Implications: ['Information cannot be destroyed', 'Hawking radiation must carry information']",
    "confidence": 0.8527918781725888,
    "phase": "published",
    "created_at": 1775551580.95232,
    "updated_at": 1775551766.185722,
    "test_results": [
      {
        "test_name": "Kolmogorov-Smirnov",
        "statistic": 0.9999938333722036,
        "p_value": 0.0,
        "passed": false,
        "details": "D = 1.0000 (vs norm)",
        "alpha": 0.05
      }
    ],
    "priority": "NORMAL",
    "publications": 0,
    "data_points_used": 5000,
    "cross_domain_links": [],
    "requires_approval": false,
    "pending_approval_at": 1775551634.223435,
    "approval_status": "approved",
    "approval_reason": "Auto-approved: confidence=0.85, tests=1, pending_cycles\u22485",
    "last_tested_at": 1775551607.159165,
    "archived_at": 0.0
  },
  {
    "id": "H050",
    "name": "Theoretical: Unitarity (from quantum_mechanics) \u2192 black_holes",
    "domain": "Astrophysics",
    "description": "Constraint transfer: Unitarity (from quantum_mechanics) \u2192 black_holes. Implications: ['Information cannot be destroyed', 'Hawking radiation must carry information']",
    "confidence": 0.42,
    "phase": "proposed",
    "created_at": 1775552372.715234,
    "updated_at": 1775552372.715234,
    "test_results": [],
    "priority": "NORMAL",
    "publications": 0,
    "data_points_used": 0,
    "cross_domain_links": [],
    "requires_approval": false,
    "pending_approval_at": 0.0,
    "approval_status": "",
    "approval_reason": "",
    "last_tested_at": 0.0,
    "archived_at": 0.0
  }
]