{
  "references": [
    {
      "authors": "Arzoumanian, D., et al.",
      "year": 2011,
      "title": "The filamentary structure of the interstellar medium: Evidence for a characteristic filament width",
      "journal": "A&A",
      "volume": "529",
      "page": "A6",
      "doi": "10.1051/0004-6361/201015161",
      "key_findings": [
        "First reported characteristic 0.1 pc filament width",
        "Analysis of 599 filaments in Aquila and 143 in Polaris",
        "Herschel 250-500 \u00b5m observations",
        "Width independent of column density (10^20-10^23 cm^-2)",
        "Width independent of central column density"
      ],
      "relevance_score": 1.0
    },
    {
      "authors": "Planck Collaboration",
      "year": 2016,
      "title": "Planck intermediate results. XXXV. Probing the role of the magnetic field in the formation of structure in molecular clouds",
      "journal": "A&A",
      "volume": "592",
      "page": "A92",
      "doi": "10.1051/0004-6361/201628617",
      "key_findings": [
        "All-sky catalog of ~10,000 filaments",
        "Confirms 0.1 pc characteristic width in diverse environments",
        "Analysis of polarization and magnetic field properties",
        "Filament width independent of Galactic latitude",
        "Cirrus clouds show same width as molecular clouds"
      ],
      "relevance_score": 0.95
    },
    {
      "authors": "Palmeirim, P., et al.",
      "year": 2013,
      "title": "The Herschel Gould Belt survey: First results from the Taurus region",
      "journal": "A&A",
      "volume": "550",
      "page": "A106",
      "doi": "10.1051/0004-6361/201220288",
      "key_findings": [
        "532 filaments analyzed in Taurus",
        "Mean width 0.11 \u00b1 0.04 pc",
        "Velocity-coherent filament analysis",
        "Correlation with N2H+ velocity structure"
      ],
      "relevance_score": 0.9
    },
    {
      "authors": "Hacar, A., et al.",
      "year": 2013,
      "title": "Decoding the velocity structure of Taurus: From large-scale turbulence to filamentary networks",
      "journal": "A&A",
      "volume": "552",
      "page": "A90",
      "doi": "10.1051/0004-6361/201220299",
      "key_findings": [
        "40 velocity-coherent filaments in Taurus",
        "Width ~0.1 pc confirmed",
        "Filament-fiber hierarchy",
        "Velocity coherence within filaments"
      ],
      "relevance_score": 0.88
    },
    {
      "authors": "Andr\u00e9, P., et al.",
      "year": 2014,
      "title": "The filamentary structure of star-forming clouds",
      "journal": "Protostars and Planets VI",
      "volume": "",
      "page": "51",
      "doi": "10.2452/PRPIPP000003",
      "key_findings": [
        "Review of filament properties across many clouds",
        "Unified model of filament formation and star formation",
        "Critical mass per unit length: 16 M_sun/pc",
        "Filament-to-core mass distribution"
      ],
      "relevance_score": 0.92
    },
    {
      "authors": "Hennebelle, P. and Andr\u00e9, P.",
      "year": 2013,
      "title": "The formation and evolution of filaments in the interstellar medium",
      "journal": "A&A",
      "volume": "557",
      "page": "A15",
      "doi": "10.1051/0004-6361/201321252",
      "key_findings": [
        "Theoretical review of filament formation",
        "Ambipolar diffusion scenarios",
        "Turbulent filament formation models",
        "Comparison with Herschel observations"
      ],
      "relevance_score": 0.85
    },
    {
      "authors": "Padoan, P., et al.",
      "year": 2001,
      "title": "The density structure of the diffuse interstellar medium: Velocity probability distribution functions",
      "journal": "ApJ",
      "volume": "553",
      "page": "877",
      "doi": "10.1086/320692",
      "key_findings": [
        "Sonic scale in supersonic turbulence",
        "Theoretical prediction for characteristic density scale",
        "Relation to filament widths"
      ],
      "relevance_score": 0.82
    },
    {
      "authors": "Kritsuk, A. G., et al.",
      "year": 2013,
      "title": "On the Density Power Spectrum in Supersonic Turbulence: Soluble Model and Numerical Simulations",
      "journal": "ApJ",
      "volume": "779",
      "page": "136",
      "doi": "10.1088/0004-637X/779/2/136",
      "key_findings": [
        "MHD simulations of supersonic turbulence",
        "Sonic scale emerges naturally in simulations",
        "Density power spectrum shows characteristic scale",
        "Comparison with Herschel observations"
      ],
      "relevance_score": 0.88
    },
    {
      "authors": "Federrath, C.",
      "year": 2016,
      "title": "The density structure of the interstellar medium: Mass-weighted versus volume-weighted statistics",
      "journal": "MNRAS",
      "volume": "457",
      "page": "399",
      "doi": "10.1093/mnras/stv2924",
      "key_findings": [
        "Turbulent driving effects on density structure",
        "Sonic scale dependence on driving parameters",
        "Implications for filament widths"
      ],
      "relevance_score": 0.8
    },
    {
      "authors": "Seifried, D. and Walch, S.",
      "year": "2015",
      "title": "Why are filaments the preferred birthplaces of protostars?",
      "journal": "MNRAS",
      "volume": "452",
      "page": "4015",
      "doi": "10.1093/mnras/stv2178",
      "key_findings": [
        "MHD simulations of filament formation",
        "Importance of magnetic fields",
        "Filament width evolution"
      ],
      "relevance_score": 0.78
    },
    {
      "authors": "Panopoulou, G. V., et al.",
      "year": 2022,
      "title": "Filament widths are log-normally distributed, not constant",
      "journal": "A&A",
      "volume": "657",
      "page": "A35",
      "doi": "10.1051/0004-6361/202141194",
      "key_findings": [
        "Re-analysis suggests width distribution, not constant",
        "Log-normal distribution with mean ~0.1 pc",
        "Implications for formation mechanisms"
      ],
      "relevance_score": 0.85
    },
    {
      "authors": "Orkisz, J., et al.",
      "year": 2019,
      "title": "Linking magnetic fields to filaments: Filamentary cloud surroundings identified by magnetic field topology",
      "journal": "A&A",
      "volume": "624",
      "page": "A110",
      "doi": "10.1051/0004-6361/201834377",
      "key_findings": [
        "Magnetic field influence on filament properties",
        "Width variations with magnetic field strength",
        "Complexities in simple sonic scale picture"
      ],
      "relevance_score": 0.75
    },
    {
      "authors": "McKee, C. F. and Ostriker, E. C.",
      "year": 2007,
      "title": "Theory of Star Formation",
      "journal": "ARA&A",
      "volume": "45",
      "page": "565",
      "doi": "10.1146/annurev.astro.45.051806.110604",
      "key_findings": [
        "Comprehensive review of star formation theory",
        "Turbulence and filament formation context",
        "Sonic scale in broader star formation context"
      ],
      "relevance_score": 0.75
    },
    {
      "authors": "Goodman, A. A., et al.",
      "year": 2020,
      "title": "The twenty first century molecular cloud: Where we stand, where we're headed",
      "journal": "Space Science Reviews",
      "volume": "216",
      "page": "61",
      "doi": "10.1007/s11214-020-00708-8",
      "key_findings": [
        "Modern perspective on molecular clouds",
        "Filament properties in current context",
        "Future observational directions"
      ],
      "relevance_score": 0.7
    }
  ],
  "datasets": [
    {
      "name": "Herschel Gould Belt Survey (HGBS)",
      "instrument": "Herschel/PACS-SPIRE",
      "wavelength_coverage": "70-500 \u00b5m",
      "angular_resolution": "5-36 arcsec",
      "spatial_coverage": "Nearby star-forming regions (< 500 pc)",
      "data_access": "http://gouldbelt-herschel.cea.fr",
      "key_papers": [
        "Andr\u00e9 et al. (2010, A&A 518, L102)",
        "Arzoumanian et al. (2011, A&A 529, A6)"
      ]
    },
    {
      "name": "Planck All-Sky Catalogue of Galactic Cold Clumps",
      "instrument": "Planck/HFI",
      "wavelength_coverage": "353-857 GHz",
      "angular_resolution": "5-10 arcmin",
      "spatial_coverage": "Full sky",
      "data_access": "https://www.cosmos.esa.int/web/planck",
      "key_papers": [
        "Planck Collaboration (2016, A&A 592, A92)",
        "Planck Collaboration (2011, A&A 536, A23)"
      ]
    },
    {
      "name": "BICEP/Keck Polarization Data",
      "instrument": "BICEP2/Keck Array",
      "wavelength_coverage": "150 GHz",
      "angular_resolution": "0.5 degrees",
      "spatial_coverage": "Southern Galactic Cap",
      "data_access": "https://bicepkeck.org",
      "key_papers": [
        "BICEP2/Keck Collaboration (2021, PRD 104, 022003)"
      ]
    },
    {
      "name": "ALMA Molecular Line Maps",
      "instrument": "ALMA",
      "wavelength_coverage": "0.3-3 mm",
      "angular_resolution": "0.01-1 arcsec",
      "spatial_coverage": "Targeted observations",
      "data_access": "https://almascience.org",
      "key_papers": [
        "Hacar et al. (2018, ApJ 861, 26)",
        "Tatematsu et al. (2016, PASJ 68, 23)"
      ]
    }
  ],
  "tools": [
    {
      "name": "Athena++",
      "type": "simulation",
      "description": "Adaptive mesh refinement MHD code for ISM simulations",
      "availability": "Open source (https://princetonuniversity.github.io/Athena-C-version/)",
      "key_papers": [
        "Stone et al. (2020, ApJS 241, 9)",
        "Kritsuk et al. (2011, ApJ 729, 1)"
      ]
    },
    {
      "name": "FLASH",
      "type": "simulation",
      "description": "Adaptive mesh MHD code with AMR",
      "availability": "Open source (http://flash.uchicago.edu/site/)",
      "key_papers": [
        "Fryxell et al. (2000, ApJS 131, 273)",
        "Federrath et al. (2010, A&A 512, A28)"
      ]
    },
    {
      "name": "getsf",
      "type": "analysis",
      "description": "Filament identification tool for Herschel data",
      "availability": "Available on request",
      "key_papers": [
        "Men'shchikov (2013, A&A 549, A91)"
      ]
    },
    {
      "name": "FilGen",
      "type": "simulation",
      "description": "Filament generation using non-equilibrium chemistry",
      "availability": "Contact authors",
      "key_papers": [
        "Clarke et al. (2018, ApJ 857, 102)"
      ]
    },
    {
      "name": "RADMC-3D",
      "type": "analysis",
      "description": "Radiative transfer for dust emission",
      "availability": "Open source (http://www.ita.uni-heidelberg.de/~dullemond/software/radmc-3d/)",
      "key_papers": [
        "Dullemond et al. (2012, RADMC-3D manual)"
      ]
    }
  ]
}